{
  "updated_at": "2026-01-06T22:56:11.344249",
  "photo_count": 17,
  "photos": [
    {
      "imagn_id": "27940304",
      "image_url": "https://cdn.imagn.com/image/thumb/800-750/27940304.jpg",
      "thumbnail_url": "https://cdn.imagn.com/image/thumb/250-225/27940304.jpg",
      "headline": "NBA: Atlanta Hawks at Toronto Raptors",
      "caption": "A view of shoes worn by Atlanta Hawks center Kristaps Porzingis (8) against the Toronto Raptors at Scotiabank Arena.",
      "photographer": "Dan Hamilton",
      "source": "Imagn Images",
      "photo_date": "2026-01-05",
      "player_name": "Kristaps Porzingis",
      "keywords": "Kristaps Porzingis",
      "added_at": "2026-01-06T22:56:11.343866",
      "player_slug": "kristaps-porzingis",
      "brand_slug": "anta"
    },
    {
      "imagn_id": "27940324",
      "image_url": "https://cdn.imagn.com/image/thumb/800-750/27940324.jpg",
      "thumbnail_url": "https://cdn.imagn.com/image/thumb/250-225/27940324.jpg",
      "headline": "NBA: Atlanta Hawks at Toronto Raptors",
      "caption": "A view of shoes worn by Toronto Raptors forward Brandon Ingram (3) against the Atlanta Hawks at Scotiabank Arena.",
      "photographer": "Dan Hamilton",
      "source": "Imagn Images",
      "photo_date": "2026-01-05",
      "player_name": "Brandon Ingram",
      "keywords": "Brandon Ingram",
      "added_at": "2026-01-06T22:56:11.344072",
      "player_slug": "brandon-ingram",
      "brand_slug": "anta"
    },
    {
      "imagn_id": "27943525",
      "image_url": "https://cdn.imagn.com/image/thumb/800-750/27943525.jpg",
      "thumbnail_url": "https://cdn.imagn.com/image/thumb/250-225/27943525.jpg",
      "headline": "NBA: Golden State Warriors at Los Angeles Clippers",
      "caption": "The Nike Kobe 4 Proto Gold Medal shoes worn by Golden State Warriors guard Stephen Curry (30) against the LA Clippers in the second half at Intuit Dome.",
      "photographer": "Kirby Lee",
      "source": "Imagn Images",
      "photo_date": "2026-01-05",
      "player_name": "Stephen Curry",
      "keywords": "Stephen Curry",
      "added_at": "2026-01-06T22:56:11.344084",
      "player_slug": "stephen-curry",
      "brand_slug": "nike"
    },
    {
      "imagn_id": "27939220",
      "image_url": "https://cdn.imagn.com/image/thumb/800-750/27939220.jpg",
      "thumbnail_url": "https://cdn.imagn.com/image/thumb/250-225/27939220.jpg",
      "headline": "NBA: New York Knicks at Detroit Pistons",
      "caption": "A detailed view of the shoes worn by New York Knicks center Karl-Anthony Towns (32) in the second half against the Detroit Pistons at Little Caesars Arena.",
      "photographer": "Rick Osentoski",
      "source": "Imagn Images",
      "photo_date": "2026-01-05",
      "player_name": "Karl-Anthony Towns",
      "keywords": "Karl-Anthony Towns",
      "added_at": "2026-01-06T22:56:11.344092",
      "player_slug": "karl-anthony-towns",
      "brand_slug": "other"
    },
    {
      "imagn_id": "27940322",
      "image_url": "https://cdn.imagn.com/image/thumb/800-750/27940322.jpg",
      "thumbnail_url": "https://cdn.imagn.com/image/thumb/250-225/27940322.jpg",
      "headline": "NBA: Atlanta Hawks at Toronto Raptors",
      "caption": "A view of a shoe worn by Toronto Raptors forward Scottie Barnes (4) against the Atlanta Hawks at Scotiabank Arena.",
      "photographer": "Dan Hamilton",
      "source": "Imagn Images",
      "photo_date": "2026-01-05",
      "player_name": "Scottie Barnes",
      "keywords": "Scottie Barnes",
      "added_at": "2026-01-06T22:56:11.344104",
      "player_slug": "scottie-barnes",
      "brand_slug": "anta"
    },
    {
      "imagn_id": "27943523",
      "image_url": "https://cdn.imagn.com/image/thumb/800-750/27943523.jpg",
      "thumbnail_url": "https://cdn.imagn.com/image/thumb/250-225/27943523.jpg",
      "headline": "NBA: Golden State Warriors at Los Angeles Clippers",
      "caption": "The Nike Kobe 4 Proto Gold Medal shoes worn by Golden State Warriors guard Stephen Curry (30) against the LA Clippers in the second half at Intuit Dome.",
      "photographer": "Kirby Lee",
      "source": "Imagn Images",
      "photo_date": "2026-01-05",
      "player_name": "Stephen Curry",
      "keywords": "Stephen Curry",
      "added_at": "2026-01-06T22:56:11.344114",
      "player_slug": "stephen-curry",
      "brand_slug": "nike"
    },
    {
      "imagn_id": "27940313",
      "image_url": "https://cdn.imagn.com/image/thumb/800-750/27940313.jpg",
      "thumbnail_url": "https://cdn.imagn.com/image/thumb/250-225/27940313.jpg",
      "headline": "NBA: Atlanta Hawks at Toronto Raptors",
      "caption": "A view of a shoe worn by Toronto Raptors forward Collin Murray-Boyles against the Atlanta Hawks at Scotiabank Arena.",
      "photographer": "Dan Hamilton",
      "source": "Imagn Images",
      "photo_date": "2026-01-05",
      "player_name": "",
      "keywords": "",
      "added_at": "2026-01-06T22:56:11.344119",
      "player_slug": "",
      "brand_slug": "anta"
    },
    {
      "imagn_id": "27940321",
      "image_url": "https://cdn.imagn.com/image/thumb/800-750/27940321.jpg",
      "thumbnail_url": "https://cdn.imagn.com/image/thumb/250-225/27940321.jpg",
      "headline": "NBA: Atlanta Hawks at Toronto Raptors",
      "caption": "A view of a shoe worn by Toronto Raptors center Sandro Mamukelashvili (54) against the Atlanta Hawks at Scotiabank Arena.",
      "photographer": "Dan Hamilton",
      "source": "Imagn Images",
      "photo_date": "2026-01-05",
      "player_name": "Sandro Mamukelashvili",
      "keywords": "Sandro Mamukelashvili",
      "added_at": "2026-01-06T22:56:11.344124",
      "player_slug": "sandro-mamukelashvili",
      "brand_slug": "anta"
    },
    {
      "imagn_id": "27943524",
      "image_url": "https://cdn.imagn.com/image/thumb/800-750/27943524.jpg",
      "thumbnail_url": "https://cdn.imagn.com/image/thumb/250-225/27943524.jpg",
      "headline": "NBA: Golden State Warriors at Los Angeles Clippers",
      "caption": "The Nike Kobe 4 Proto Gold Medal shoes worn by Golden State Warriors guard Stephen Curry (30) against the LA Clippers in the second half at Intuit Dome.",
      "photographer": "Kirby Lee",
      "source": "Imagn Images",
      "photo_date": "2026-01-05",
      "player_name": "Stephen Curry",
      "keywords": "Stephen Curry",
      "added_at": "2026-01-06T22:56:11.344134",
      "player_slug": "stephen-curry",
      "brand_slug": "nike"
    },
    {
      "imagn_id": "27938490",
      "image_url": "https://cdn.imagn.com/image/thumb/800-750/27938490.jpg",
      "thumbnail_url": "https://cdn.imagn.com/image/thumb/250-225/27938490.jpg",
      "headline": "NBA: New York Knicks at Detroit Pistons",
      "caption": "A detailed view of the shoes worn by New York Knicks guard Jalen Brunson (11) in the first half against the Detroit Pistons at Little Caesars Arena.",
      "photographer": "Rick Osentoski",
      "source": "Imagn Images",
      "photo_date": "2026-01-05",
      "player_name": "Jalen Brunson",
      "keywords": "Jalen Brunson",
      "added_at": "2026-01-06T22:56:11.344140",
      "player_slug": "jalen-brunson",
      "brand_slug": "other"
    },
    {
      "imagn_id": "27933350",
      "image_url": "https://cdn.imagn.com/image/thumb/800-750/27933350.jpg",
      "thumbnail_url": "https://cdn.imagn.com/image/thumb/250-225/27933350.jpg",
      "headline": "NBA: Indiana Pacers at Orlando Magic",
      "caption": "A detailed view of the shoes worn by Orlando Magic forward Paolo Banchero (5) during the game against the Indiana Pacers at Kia Center.",
      "photographer": "Mike Watters",
      "source": "Imagn Images",
      "photo_date": "2026-01-04",
      "player_name": "Paolo Banchero",
      "keywords": "Paolo Banchero",
      "added_at": "2026-01-06T22:56:11.344147",
      "player_slug": "paolo-banchero",
      "brand_slug": "other"
    },
    {
      "imagn_id": "27933351",
      "image_url": "https://cdn.imagn.com/image/thumb/800-750/27933351.jpg",
      "thumbnail_url": "https://cdn.imagn.com/image/thumb/250-225/27933351.jpg",
      "headline": "NBA: Indiana Pacers at Orlando Magic",
      "caption": "A detailed view of the shoes worn by Indiana Pacers center Micah Potter (11) during the game against the Orlando Magic at Kia Center.",
      "photographer": "Mike Watters",
      "source": "Imagn Images",
      "photo_date": "2026-01-04",
      "player_name": "Micah Potter",
      "keywords": "Micah Potter",
      "added_at": "2026-01-06T22:56:11.344154",
      "player_slug": "micah-potter",
      "brand_slug": "other"
    },
    {
      "imagn_id": "27933347",
      "image_url": "https://cdn.imagn.com/image/thumb/800-750/27933347.jpg",
      "thumbnail_url": "https://cdn.imagn.com/image/thumb/250-225/27933347.jpg",
      "headline": "NBA: Indiana Pacers at Orlando Magic",
      "caption": "A detailed view of the shoes worn by Indiana Pacers forward Pascal Siakam (43) during the game against the Orlando Magic at Kia Center.",
      "photographer": "Mike Watters",
      "source": "Imagn Images",
      "photo_date": "2026-01-04",
      "player_name": "Pascal Siakam",
      "keywords": "",
      "added_at": "2026-01-06T22:56:11.344161",
      "player_slug": "pascal-siakam",
      "brand_slug": "other"
    },
    {
      "imagn_id": "27933346",
      "image_url": "https://cdn.imagn.com/image/thumb/800-750/27933346.jpg",
      "thumbnail_url": "https://cdn.imagn.com/image/thumb/250-225/27933346.jpg",
      "headline": "NBA: Indiana Pacers at Orlando Magic",
      "caption": "A detailed view of the shoes worn by Indiana Pacers center Jay Huff (32) during the game against the Orlando Magic at Kia Center.",
      "photographer": "Mike Watters",
      "source": "Imagn Images",
      "photo_date": "2026-01-04",
      "player_name": "Jay Huff",
      "keywords": "Jay Huff",
      "added_at": "2026-01-06T22:56:11.344167",
      "player_slug": "jay-huff",
      "brand_slug": "other"
    },
    {
      "imagn_id": "27933348",
      "image_url": "https://cdn.imagn.com/image/thumb/800-750/27933348.jpg",
      "thumbnail_url": "https://cdn.imagn.com/image/thumb/250-225/27933348.jpg",
      "headline": "NBA: Indiana Pacers at Orlando Magic",
      "caption": "A detailed view of the shoes worn by Orlando Magic guard Desmond Bane (3) during the game against the Indiana Pacers at Kia Center.",
      "photographer": "Mike Watters",
      "source": "Imagn Images",
      "photo_date": "2026-01-04",
      "player_name": "Desmond Bane",
      "keywords": "Desmond Bane",
      "added_at": "2026-01-06T22:56:11.344173",
      "player_slug": "desmond-bane",
      "brand_slug": "other"
    },
    {
      "imagn_id": "27926340",
      "image_url": "https://cdn.imagn.com/image/thumb/800-750/27926340.jpg",
      "thumbnail_url": "https://cdn.imagn.com/image/thumb/250-225/27926340.jpg",
      "headline": "NBA: Atlanta Hawks at Toronto Raptors",
      "caption": "A general view of the basketball shoes of Atlanta Hawks forward Mouhamed Gueye (18) during the warmup before a game against the Toronto Raptors at Scotiabank Arena.",
      "photographer": "Nick Turchiaro",
      "source": "Imagn Images",
      "photo_date": "2026-01-03",
      "player_name": "Mouhamed Gueye",
      "keywords": "Mouhamed Gueye",
      "added_at": "2026-01-06T22:56:11.344179",
      "player_slug": "mouhamed-gueye",
      "brand_slug": "anta"
    },
    {
      "imagn_id": "27926345",
      "image_url": "https://cdn.imagn.com/image/thumb/800-750/27926345.jpg",
      "thumbnail_url": "https://cdn.imagn.com/image/thumb/250-225/27926345.jpg",
      "headline": "NBA: Atlanta Hawks at Toronto Raptors",
      "caption": "A general view of the basketball shoes of Toronto Raptors forward Scottie Barnes (4) during the warmup before a game against the Atlanta Hawks at Scotiabank Arena.",
      "photographer": "Nick Turchiaro",
      "source": "Imagn Images",
      "photo_date": "2026-01-03",
      "player_name": "Scottie Barnes",
      "keywords": "Scottie Barnes",
      "added_at": "2026-01-06T22:56:11.344186",
      "player_slug": "scottie-barnes",
      "brand_slug": "anta"
    }
  ]
}